mpai_cae_arp/__init__.py
mpai_cae_arp/audio/__init__.py
mpai_cae_arp/audio/_audio.py
mpai_cae_arp/audio/_noise.py
mpai_cae_arp/audio/standards.py
mpai_cae_arp/audio/utils.py
mpai_cae_arp/files.py
mpai_cae_arp/io.py
mpai_cae_arp/network/__init__.py
mpai_cae_arp/network/arp_pb2.py
mpai_cae_arp/network/arp_pb2.pyi
mpai_cae_arp/network/arp_pb2_grpc.py
mpai_cae_arp/network/arp_pb2_grpc.pyi
mpai_cae_arp/network/utils.py
mpai_cae_arp/py.typed
mpai_cae_arp/time.py
mpai_cae_arp/types/__init__.py
mpai_cae_arp/types/_irregularity.py
mpai_cae_arp/types/_restoration.py
mpai_cae_arp/types/schema.py
mpai_cae_arp-0.5.4.dist-info/LICENSE
mpai_cae_arp-0.5.4.dist-info/METADATA
mpai_cae_arp-0.5.4.dist-info/WHEEL
mpai_cae_arp-0.5.4.dist-info/RECORD
