Metadata-Version: 2.1
Name: mpai-cae-arp
Version: 0.5.4
Summary: The MPAI CAE-ARP software API
License: GPLv3
Keywords: mpai,cae,arp,audio,processing,artificial intelligence
Author: Matteo Spanio
Author-email: spanio@dei.unipd.it
Requires-Python: >=3.10,<4.0
Classifier: Development Status :: 4 - Beta
Classifier: Intended Audience :: Developers
Classifier: License :: OSI Approved :: GNU General Public License v3 (GPLv3)
Classifier: License :: Other/Proprietary License
Classifier: Operating System :: OS Independent
Classifier: Programming Language :: Python :: 3
Classifier: Programming Language :: Python :: 3.10
Classifier: Programming Language :: Python :: 3.11
Classifier: Programming Language :: Python :: 3.12
Requires-Dist: grpcio-tools (>=1.59.0,<2.0.0)
Requires-Dist: librosa (>=0.10.1,<0.11.0)
Requires-Dist: numpy (>=1.24.4,<2.0.0)
Requires-Dist: pydantic (>=2.4.0,<3.0.0)
Requires-Dist: pyyaml (>=6.0,<7.0)
